tilert-0.1.1.dist-info/METADATA
tilert-0.1.1.dist-info/WHEEL
tilert-0.1.1.dist-info/licenses/LICENSE
tilert-0.1.1.dist-info/top_level.txt
tilert/__init__.py
tilert/__version__.py
tilert/generate.py
tilert/libtilert.so
tilert/models/__init__.py
tilert/models/base.py
tilert/models/deepseek_config.py
tilert/models/deepseek_v3_2/dsa_show_hands.py
tilert/models/deepseek_v3_2/model_args.py
tilert/models/deepseek_v3_2/params.py
tilert/models/preprocess/__init__.py
tilert/models/preprocess/weight_utils.py
tilert/models/utils.py
tilert/tilert_init.py
tilert/utils.py
tilert-0.1.1.dist-info/RECORD
