Metadata-Version: 2.4
Name: tilert
Version: 0.1.1
Summary: TileRT: Tile-Based Runtime for Ultra-Low-Latency LLM Inference.
Author-email: TileRT-team <tile-ai@outlook.com>
License: MIT
Project-URL: Homepage, https://github.com/tile-ai/TileRT
Project-URL: Issues, https://github.com/tile-ai/TileRT/issues
Classifier: Programming Language :: Python :: 3.11
Classifier: Programming Language :: Python :: 3.12
Classifier: Operating System :: OS Independent
Classifier: Topic :: Software Development :: Libraries
Requires-Python: >=3.11
License-File: LICENSE
Requires-Dist: torch
Provides-Extra: dev
Requires-Dist: pytest>=7.0.0; extra == "dev"
Requires-Dist: black==25.1.0; extra == "dev"
Requires-Dist: flake8==7.1.2; extra == "dev"
Requires-Dist: flake8-bugbear==24.12.12; extra == "dev"
Requires-Dist: flake8-comprehensions==3.16.0; extra == "dev"
Requires-Dist: flake8-docstrings==1.7.0; extra == "dev"
Requires-Dist: flake8-simplify==0.21.0; extra == "dev"
Requires-Dist: flake8-unused-arguments==0.0.13; extra == "dev"
Requires-Dist: flake8-variables-names==0.0.6; extra == "dev"
Requires-Dist: flake8-return==1.2.0; extra == "dev"
Requires-Dist: flake8-print==5.0.0; extra == "dev"
Requires-Dist: isort==6.0.1; extra == "dev"
Requires-Dist: mypy==1.15.0; extra == "dev"
Requires-Dist: bandit==1.8.3; extra == "dev"
Requires-Dist: pyupgrade==3.19.1; extra == "dev"
Requires-Dist: commitizen==4.4.1; extra == "dev"
Requires-Dist: codespell==2.4.1; extra == "dev"
Requires-Dist: pre-commit>=3.0.0; extra == "dev"
Requires-Dist: mdformat==0.7.17; extra == "dev"
Requires-Dist: mdformat-gfm==0.4.1; extra == "dev"
Requires-Dist: mdformat-frontmatter==2.0.8; extra == "dev"
Requires-Dist: mdformat-myst==0.2.1; extra == "dev"
Requires-Dist: mdformat-tables==1.0.0; extra == "dev"
Requires-Dist: mdformat-toc==0.3.0; extra == "dev"
Requires-Dist: mdformat-black==0.1.1; extra == "dev"
Requires-Dist: types-setuptools; extra == "dev"
Requires-Dist: types-requests; extra == "dev"
Requires-Dist: types-urllib3; extra == "dev"
Requires-Dist: types-six; extra == "dev"
Requires-Dist: tomli==2.2.1; extra == "dev"
Dynamic: license-file
Dynamic: requires-python
